{
  "id": "52c7cf36-8737-4566-8fb0-aacbdf014c34",
  "slug": "flip-game-ii",
  "title": "Flip Game II",
  "difficulty": "medium",
  "descriptionHtml": "",
  "patterns": [
    "math",
    "dynamic-programming",
    "backtracking",
    "memoization",
    "game-theory"
  ],
  "constraints": {},
  "examples": [],
  "testCases": [
    {
      "input": "\"++++\"\n\"+\"",
      "expectedOutput": "",
      "isHidden": false
    }
  ],
  "canonicalSolutions": [
    {
      "language": "cpp",
      "code": "// Time:  O(n + c^2), c is max length of consecutive '+'\n// Space: O(c)\n\n// The best theory solution (DP, O(n + c^2)) could be seen here:\n// https://leetcode.com/problems/flip-game-ii/discuss/73954/theory-matters-from-backtracking128ms-to-dp-0ms\nclass Solution {\npublic:\n    bool canWin(string s) {\n        replace(s.begin(), s.end(), '-', ' ');\n        istringstream in(s);\n        int g_final = 0;\n        vector<int> g;  // Sprague-Grundy function of 0 ~ maxlen, O(n) space\n        for (string t; in >> t; ) {  // Split the string\n            int p = t.size();\n            while (g.size() <= p) {  // O(c) time\n                string x{t};\n                int i = 0, j = g.size() - 2;\n                while (i <= j) {  // The S-G value of all subgame states, O(c) time\n                    // Theorem 2: g[game] = g[subgame1]^g[subgame2]^g[subgame3]...;\n                    x[g[i++] ^ g[j--]] = '-';\n                }\n                // Find first missing number.\n                g.emplace_back(x.find('+'));\n            }\n            g_final ^= g[p];\n        }\n        return g_final;  // Theorem 1: First player must win iff g(current_state) != 0\n    }\n};\n\n\n// Time:  O(n + c^3 * 2^c * logc), n is length of string, c is count of \"++\"\n// Space: O(c * 2^c)\n// hash solution.\nclass Solution2 {\npublic:\n    struct multiset_hash {\n        std::size_t operator() (const multiset<int>& set) const {\n            string set_string;\n            for (const auto& i : set) {\n                set_string.append(to_string(i) + \" \");\n            }\n            return hash<string>()(set_string); \n        }\n    };\n\n    bool canWin(string s) {\n        const int n = s.length();\n        multiset<int> consecutives;\n        for (int i = 0; i < n - 1; ++i) {  // O(n) time\n            if (s[i] == '+') {\n                int c = 1;\n                for (; i < n - 1 && s[i + 1] == '+'; ++i, ++c);\n                if (c >= 2) {\n                    consecutives.emplace(c);\n                }\n            }\n        }\n        return canWinHelper(consecutives);\n    }\n\nprivate:\n    bool canWinHelper(const multiset<int>& consecutives) {  // O(2^c) time\n        if (!lookup_.count(consecutives)) {\n            bool is_win = false;\n            for (auto it = consecutives.cbegin(); !is_win && it != consecutives.cend(); ++it) {  // O(c) time\n                const int c = *it;\n                multiset<int> next_consecutives(consecutives);\n                next_consecutives.erase(next_consecutives.find(c));\n                for (int i = 0; !is_win && i < c - 1; ++i) {  // O(clogc) time\n                    if (i >= 2) {\n                        next_consecutives.emplace(i);\n                    }\n                    if (c - 2 - i >= 2) {\n                        next_consecutives.emplace(c - 2 - i);\n                    }\n                    is_win = !canWinHelper(next_consecutives);\n                    if (i >= 2) {\n                        next_consecutives.erase(next_consecutives.find(i));\n                    }\n                    if (c - 2 - i >= 2) {\n                        next_consecutives.erase(next_consecutives.find(c - 2 - i));\n                    }\n                    lookup_[consecutives] = is_win;  // O(c) time\n                }\n            }\n        }\n        return lookup_[consecutives];\n    }\n    unordered_map<multiset<int>, bool, multiset_hash> lookup_;\n};\n\n\n// Time:  O(n + c * n * 2^c), try all the possible game strings,\n//                            and each string would have c choices to become the next string \n// Space: O(n * 2^c), keep all the possible game strings\n// hash solution.\nclass Solution3 {\npublic:\n    bool canWin(string s) {\n        if (!lookup_.count(s)) {\n            const int n = s.length();\n            bool is_win = false; \n            for (int i = 0; !is_win && i < n - 1; ++i) {\n                if (s[i] == '+') {\n                    for (; !is_win && i < n - 1 && s[i + 1] == '+'; ++i) {\n                        s[i] = s[i + 1] = '-';\n                        is_win = !canWin(s); \n                        s[i] = s[i + 1] = '+';\n                        lookup_[s] = is_win;\n                    }\n                }\n            }\n        }\n        return lookup_[s];  \n    }\nprivate:\n    unordered_map<string, bool> lookup_;\n};\n\n\n// Time:  O(n * c!), n is length of string, c is count of \"++\"\n// Space: O(c), recursion would be called at most c in depth.\n//              Besides, no extra space in each depth for the modified string.\nclass Solution4 {\npublic:\n    bool canWin(string s) {\n        const int n = s.length();\n        bool is_win = false; \n        for (int i = 0; !is_win && i < n - 1; ++i) {  // O(n) time\n            if (s[i] == '+') {\n                for (; !is_win && i < n - 1 && s[i + 1] == '+'; ++i) {  // O(c) time\n                    s[i] = s[i + 1] = '-';\n                    // t(n, c) = c * t(n, c - 1) + n = ... = c! * t(n, 0) + n * c! * (1/0! + 1/1! + ... 1/c!)\n                    // = n * c! + n * c! * O(e) = O(n * c!)\n                    is_win = !canWin(s); \n                     s[i] = s[i + 1] = '+';\n                }\n            }\n        }\n        return is_win;  \n    }\n};",
      "timeComplexity": "",
      "spaceComplexity": ""
    },
    {
      "language": "python",
      "code": "# Time:  O(n + c^2)\n# Space: O(c)\n\nimport itertools\nimport re\n\n\n# The best theory solution (DP, O(n + c^2)) could be seen here:\n# https://leetcode.com/problems/flip-game-ii/discuss/73954/theory-matters-from-backtracking128ms-to-dp-0ms\nclass Solution(object):\n    def canWin(self, s):\n        g, g_final = [0], 0\n        for p in itertools.imap(len, re.split('-+', s)):\n            while len(g) <= p:\n                # Theorem 2: g[game] = g[subgame1]^g[subgame2]^g[subgame3]...\n                # and find first missing number.\n                g += min(set(xrange(p)) - {x^y for x, y in itertools.izip(g[:len(g)/2], g[-2:-len(g)/2-2:-1])}),\n            g_final ^= g[p]\n        return g_final > 0  # Theorem 1: First player must win iff g(current_state) != 0\n\n\n# Time:  O(n + c^3 * 2^c * logc), n is length of string, c is count of \"++\"\n# Space: O(c * 2^c)\n# hash solution.\n# We have total O(2^c) game strings,\n# and each hash key in hash table would cost O(c),\n# each one has O(c) choices to the next one,\n# and each one would cost O(clogc) to sort,\n# so we get O((c * 2^c) * (c * clogc)) = O(c^3 * 2^c * logc) time.\n# To cache the results of all combinations, thus O(c * 2^c) space.\nclass Solution2(object):\n    def canWin(self, s):\n        \"\"\"\n        :type s: str\n        :rtype: bool\n        \"\"\"\n        lookup = {}\n\n        def canWinHelper(consecutives):                                         # O(2^c) time\n            consecutives = tuple(sorted(c for c in consecutives if c >= 2))     # O(clogc) time\n            if consecutives not in lookup:\n                lookup[consecutives] = any(not canWinHelper(consecutives[:i] + (j, c-2-j) + consecutives[i+1:])  # O(c) time\n                                           for i, c in enumerate(consecutives)  # O(c) time\n                                           for j in xrange(c - 1))              # O(c) time\n            return lookup[consecutives]                                         # O(c) time\n\n        # re.findall: O(n) time, canWinHelper: O(c) in depth\n        return canWinHelper(map(len, re.findall(r'\\+\\++', s)))\n\n\n# Time:  O(c * n * c!), n is length of string, c is count of \"++\"\n# Space: O(c * n), recursion would be called at most c in depth.\n#                  Besides, it costs n space for modifying string at each depth.\nclass Solution3(object):\n    def canWin(self, s):\n        \"\"\"\n        :type s: str\n        :rtype: bool\n        \"\"\"\n        i, n = 0, len(s) - 1\n        is_win = False\n        while not is_win and i < n:                                     # O(n) time\n            if s[i] == '+':\n                while not is_win and i < n and s[i+1] == '+':           # O(c) time\n                     # t(n, c) = c * (t(n, c-1) + n) + n = ...\n                     # = c! * t(n, 0) + n * c! * (c + 1) * (1/0! + 1/1! + ... 1/c!)\n                     # = n * c! + n * c! * (c + 1) * O(e) = O(c * n * c!)\n                    is_win = not self.canWin(s[:i] + '--' + s[i+2:])    # O(n) space\n                    i += 1\n            i += 1\n        return is_win",
      "timeComplexity": "",
      "spaceComplexity": ""
    }
  ],
  "editorial": {
    "approach": "",
    "explanation": "",
    "keyInsight": "",
    "commonMistakes": []
  }
}