{
  "id": "c494ac4f-4155-4594-9b0e-d04cc0fbf8d0",
  "slug": "insert-into-a-binary-search-tree",
  "title": "Insert into a Binary Search Tree",
  "difficulty": "medium",
  "descriptionHtml": "<p>You are given the <code>root</code> node of a binary search tree (BST) and a <code>value</code> to insert into the tree. Return <em>the root node of the BST after the insertion</em>. It is <strong>guaranteed</strong> that the new value does not exist in the original BST.</p>\n\n<p><strong>Notice</strong>&nbsp;that there may exist&nbsp;multiple valid ways for the&nbsp;insertion, as long as the tree remains a BST after insertion. You can return <strong>any of them</strong>.</p>\n\n<p>&nbsp;</p>\n<p><strong class=\"example\">Example 1:</strong></p>\n<img alt=\"\" src=\"https://assets.leetcode.com/uploads/2020/10/05/insertbst.jpg\" style=\"width: 752px; height: 221px;\" />\n<pre>\n<strong>Input:</strong> root = [4,2,7,1,3], val = 5\n<strong>Output:</strong> [4,2,7,1,3,5]\n<strong>Explanation:</strong> Another accepted tree is:\n<img alt=\"\" src=\"https://assets.leetcode.com/uploads/2020/10/05/bst.jpg\" style=\"width: 352px; height: 301px;\" />\n</pre>\n\n<p><strong class=\"example\">Example 2:</strong></p>\n\n<pre>\n<strong>Input:</strong> root = [40,20,60,10,30,50,70], val = 25\n<strong>Output:</strong> [40,20,60,10,30,50,70,null,null,25]\n</pre>\n\n<p><strong class=\"example\">Example 3:</strong></p>\n\n<pre>\n<strong>Input:</strong> root = [4,2,7,1,3,null,null,null,null,null,null], val = 5\n<strong>Output:</strong> [4,2,7,1,3,5]\n</pre>\n\n<p>&nbsp;</p>\n<p><strong>Constraints:</strong></p>\n\n<ul>\n\t<li>The number of nodes in&nbsp;the tree will be in the range <code>[0,&nbsp;10<sup>4</sup>]</code>.</li>\n\t<li><code>-10<sup>8</sup> &lt;= Node.val &lt;= 10<sup>8</sup></code></li>\n\t<li>All the values <code>Node.val</code> are <strong>unique</strong>.</li>\n\t<li><code>-10<sup>8</sup> &lt;= val &lt;= 10<sup>8</sup></code></li>\n\t<li>It&#39;s <strong>guaranteed</strong> that <code>val</code> does not exist in the original BST.</li>\n</ul>\n",
  "patterns": [
    "tree",
    "binary-search-tree",
    "binary-tree"
  ],
  "constraints": {},
  "examples": [],
  "testCases": [],
  "canonicalSolutions": [
    {
      "language": "cpp",
      "code": "// Time:  O(h)\n// Space: O(1)\n\n/**\n * Definition for a binary tree node.\n * struct TreeNode {\n *     int val;\n *     TreeNode *left;\n *     TreeNode *right;\n *     TreeNode(int x) : val(x), left(NULL), right(NULL) {}\n * };\n */\nclass Solution {\npublic:\n    TreeNode* insertIntoBST(TreeNode* root, int val) {\n        TreeNode *curr = root, *parent = nullptr;\n        while (curr) {\n            parent = curr;\n            if (val <= curr->val) {\n                curr = curr->left;\n            } else {\n                curr = curr->right;\n            }\n        }\n        if (!parent) {\n            root = new TreeNode(val);\n        } else if (val <= parent->val) {\n            parent->left = new TreeNode(val);\n        } else {\n            parent->right = new TreeNode(val);\n        }\n        return root;\n    }\n};\n\n\n// Time:  O(h)\n// Space: O(h)\nclass Solution2 {\npublic:\n    TreeNode* insertIntoBST(TreeNode* root, int val) {\n        if (!root) {\n            root = new TreeNode(val);\n        } else {\n            if (val <= root->val) {\n                root->left = insertIntoBST(root->left, val);\n            } else {\n                root->right = insertIntoBST(root->right, val);\n            }\n        }\n        return root;\n    }\n};",
      "timeComplexity": "",
      "spaceComplexity": ""
    },
    {
      "language": "python",
      "code": "# Time:  O(h)\n# Space: O(1)\n\nclass TreeNode(object):\n    def __init__(self, x):\n        self.val = x\n        self.left = None\n        self.right = None\n\n\nclass Solution(object):\n    def insertIntoBST(self, root, val):\n        \"\"\"\n        :type root: TreeNode\n        :type val: int\n        :rtype: TreeNode\n        \"\"\"\n        curr, parent = root, None\n        while curr:\n            parent = curr\n            if val <= curr.val:\n                curr = curr.left\n            else:\n                curr = curr.right\n        if not parent:\n            root = TreeNode(val)\n        elif val <= parent.val:\n            parent.left = TreeNode(val)\n        else:\n            parent.right = TreeNode(val)\n        return root\n\n\n# Time:  O(h)\n# Space: O(h)\nclass Solution2(object):\n    def insertIntoBST(self, root, val):\n        \"\"\"\n        :type root: TreeNode\n        :type val: int\n        :rtype: TreeNode\n        \"\"\"\n        if not root:\n            root = TreeNode(val)\n        else:\n            if val <= root.val:\n                root.left = self.insertIntoBST(root.left, val)\n            else:\n                root.right = self.insertIntoBST(root.right, val)\n        return root",
      "timeComplexity": "",
      "spaceComplexity": ""
    }
  ],
  "editorial": {
    "approach": "",
    "explanation": "",
    "keyInsight": "",
    "commonMistakes": []
  }
}