{
  "id": "c052c9c0-6116-4f4c-bc0c-6afb993d36e9",
  "slug": "minimum-initial-energy-to-finish-tasks",
  "title": "Minimum Initial Energy to Finish Tasks",
  "difficulty": "hard",
  "descriptionHtml": "<p>You are given an array <code>tasks</code> where <code>tasks[i] = [actual<sub>i</sub>, minimum<sub>i</sub>]</code>:</p>\n\n<ul>\n\t<li><code>actual<sub>i</sub></code> is the actual amount of energy you <strong>spend to finish</strong> the <code>i<sup>th</sup></code> task.</li>\n\t<li><code>minimum<sub>i</sub></code> is the minimum amount of energy you <strong>require to begin</strong> the <code>i<sup>th</sup></code> task.</li>\n</ul>\n\n<p>For example, if the task is <code>[10, 12]</code> and your current energy is <code>11</code>, you cannot start this task. However, if your current energy is <code>13</code>, you can complete this task, and your energy will be <code>3</code> after finishing it.</p>\n\n<p>You can finish the tasks in <strong>any order</strong> you like.</p>\n\n<p>Return <em>the <strong>minimum</strong> initial amount of energy you will need</em> <em>to finish all the tasks</em>.</p>\n\n<p>&nbsp;</p>\n<p><strong class=\"example\">Example 1:</strong></p>\n\n<pre>\n<strong>Input:</strong> tasks = [[1,2],[2,4],[4,8]]\n<strong>Output:</strong> 8\n<strong>Explanation:</strong>\nStarting with 8 energy, we finish the tasks in the following order:\n    - 3rd task. Now energy = 8 - 4 = 4.\n    - 2nd task. Now energy = 4 - 2 = 2.\n    - 1st task. Now energy = 2 - 1 = 1.\nNotice that even though we have leftover energy, starting with 7 energy does not work because we cannot do the 3rd task.</pre>\n\n<p><strong class=\"example\">Example 2:</strong></p>\n\n<pre>\n<strong>Input:</strong> tasks = [[1,3],[2,4],[10,11],[10,12],[8,9]]\n<strong>Output:</strong> 32\n<strong>Explanation:</strong>\nStarting with 32 energy, we finish the tasks in the following order:\n    - 1st task. Now energy = 32 - 1 = 31.\n    - 2nd task. Now energy = 31 - 2 = 29.\n    - 3rd task. Now energy = 29 - 10 = 19.\n    - 4th task. Now energy = 19 - 10 = 9.\n    - 5th task. Now energy = 9 - 8 = 1.</pre>\n\n<p><strong class=\"example\">Example 3:</strong></p>\n\n<pre>\n<strong>Input:</strong> tasks = [[1,7],[2,8],[3,9],[4,10],[5,11],[6,12]]\n<strong>Output:</strong> 27\n<strong>Explanation:</strong>\nStarting with 27 energy, we finish the tasks in the following order:\n    - 5th task. Now energy = 27 - 5 = 22.\n    - 2nd task. Now energy = 22 - 2 = 20.\n    - 3rd task. Now energy = 20 - 3 = 17.\n    - 1st task. Now energy = 17 - 1 = 16.\n    - 4th task. Now energy = 16 - 4 = 12.\n    - 6th task. Now energy = 12 - 6 = 6.\n</pre>\n\n<p>&nbsp;</p>\n<p><strong>Constraints:</strong></p>\n\n<ul>\n\t<li><code>1 &lt;= tasks.length &lt;= 10<sup>5</sup></code></li>\n\t<li><code>1 &lt;= actual<sub>​i</sub>&nbsp;&lt;= minimum<sub>i</sub>&nbsp;&lt;= 10<sup>4</sup></code></li>\n</ul>\n",
  "patterns": [
    "array",
    "greedy",
    "sorting"
  ],
  "constraints": {},
  "examples": [],
  "testCases": [
    {
      "input": "[[1,2],[2,4],[4,8]]\n[[1,3],[2,4],[10,11],[10,12],[8,9]]\n[[1,7],[2,8],[3,9],[4,10],[5,11],[6,12]]",
      "expectedOutput": "",
      "isHidden": false
    }
  ],
  "canonicalSolutions": [
    {
      "language": "cpp",
      "code": "// Time:  O(nlogn)\n// Space: O(1)\n\nclass Solution {\npublic:\n    int minimumEffort(vector<vector<int>>& tasks) {\n        sort(begin(tasks), end(tasks),\n             [](const auto& a, const auto& b) {\n                 return a[1] - a[0] < b[1] - b[0];  // sort by waste in asc\n             });\n        int result = 0;\n        // you can see proof here, https://leetcode.com/problems/minimum-initial-energy-to-finish-tasks/discuss/944633/Explanation-on-why-sort-by-difference\n        for (const auto& task : tasks) {  // we need to pick all the wastes, so greedily to pick the least waste first is always better\n            result = max(result + task[0], task[1]);\n        }\n        return result;\n    }\n};\n\n// Time:  O(nlogn)\n// Space: O(1)\nclass Solution2 {\npublic:\n    int minimumEffort(vector<vector<int>>& tasks) {\n        sort(begin(tasks), end(tasks),\n             [](const auto& a, const auto& b) {\n                 return a[1] - a[0] > b[1] - b[0];  // sort by save in desc\n             });\n        int result = 0, curr = 0;\n        for (const auto& task : tasks) {  // we need to pick all the saves, so greedily to pick the most save first is always better\n            result += max(task[1] - curr, 0);\n            curr = max(curr, task[1]) - task[0];\n        }\n        return result;\n    }\n};",
      "timeComplexity": "",
      "spaceComplexity": ""
    },
    {
      "language": "python",
      "code": "# Time:  O(nlogn)\n# Space: O(1)\n\nclass Solution(object):\n    def minimumEffort(self, tasks):\n        \"\"\"\n        :type tasks: List[List[int]]\n        :rtype: int\n        \"\"\"\n        tasks.sort(key=lambda x: x[1]-x[0])  # sort by waste in asc\n        result = 0\n        # you can see proof here, https://leetcode.com/problems/minimum-initial-energy-to-finish-tasks/discuss/944633/Explanation-on-why-sort-by-difference\n        for a, m in tasks:  # we need to pick all the wastes, so greedily to pick the least waste first is always better\n            result = max(result+a, m)\n        return result\n\n\n# Time:  O(nlogn)\n# Space: O(1)\nclass Solution2(object):\n    def minimumEffort(self, tasks):\n        \"\"\"\n        :type tasks: List[List[int]]\n        :rtype: int\n        \"\"\"\n        tasks.sort(key=lambda x: x[0]-x[1])  # sort by save in desc\n        result = curr = 0\n        for a, m in tasks:  # we need to pick all the saves, so greedily to pick the most save first is always better\n            result += max(m-curr, 0)\n            curr = max(curr, m)-a\n        return result",
      "timeComplexity": "",
      "spaceComplexity": ""
    }
  ],
  "editorial": {
    "approach": "",
    "explanation": "",
    "keyInsight": "",
    "commonMistakes": []
  }
}