{
  "id": "5616e7e3-f988-4d1b-a69b-e7aa4c19fc79",
  "slug": "painting-a-grid-with-three-different-colors",
  "title": "Painting a Grid With Three Different Colors",
  "difficulty": "hard",
  "descriptionHtml": "<p>You are given two integers <code>m</code> and <code>n</code>. Consider an <code>m x n</code> grid where each cell is initially white. You can paint each cell <strong>red</strong>, <strong>green</strong>, or <strong>blue</strong>. All cells <strong>must</strong> be painted.</p>\n\n<p>Return<em> the number of ways to color the grid with <strong>no two adjacent cells having the same color</strong></em>. Since the answer can be very large, return it <strong>modulo</strong> <code>10<sup>9</sup> + 7</code>.</p>\n\n<p>&nbsp;</p>\n<p><strong class=\"example\">Example 1:</strong></p>\n<img alt=\"\" src=\"https://assets.leetcode.com/uploads/2021/06/22/colorthegrid.png\" style=\"width: 200px; height: 50px;\" />\n<pre>\n<strong>Input:</strong> m = 1, n = 1\n<strong>Output:</strong> 3\n<strong>Explanation:</strong> The three possible colorings are shown in the image above.\n</pre>\n\n<p><strong class=\"example\">Example 2:</strong></p>\n<img alt=\"\" src=\"https://assets.leetcode.com/uploads/2021/06/22/copy-of-colorthegrid.png\" style=\"width: 321px; height: 121px;\" />\n<pre>\n<strong>Input:</strong> m = 1, n = 2\n<strong>Output:</strong> 6\n<strong>Explanation:</strong> The six possible colorings are shown in the image above.\n</pre>\n\n<p><strong class=\"example\">Example 3:</strong></p>\n\n<pre>\n<strong>Input:</strong> m = 5, n = 5\n<strong>Output:</strong> 580986\n</pre>\n\n<p>&nbsp;</p>\n<p><strong>Constraints:</strong></p>\n\n<ul>\n\t<li><code>1 &lt;= m &lt;= 5</code></li>\n\t<li><code>1 &lt;= n &lt;= 1000</code></li>\n</ul>\n",
  "patterns": [
    "dynamic-programming"
  ],
  "constraints": {},
  "examples": [],
  "testCases": [
    {
      "input": "1\n1\n1\n2\n5\n5",
      "expectedOutput": "",
      "isHidden": false
    }
  ],
  "canonicalSolutions": [
    {
      "language": "cpp",
      "code": "// Time:  O(m * 2^m + 3^m + 2^(3 * m) * logn) = O(2^(3 * m) * logn)\n// Space: O(2^(2 * m))\n\n// better complexity for small m, super large n\nclass Solution {\npublic:\n    int colorTheGrid(int m, int n) {\n        if (m > n) {\n            swap(m, n);\n        }\n        const int basis = pow(3, m - 1);\n        vector<int> masks;\n        backtracking(-1, -1, basis, &masks);  // Time: O(2^m), Space: O(2^m)\n        assert(size(masks) == 3 * pow(2, m - 1));\n        unordered_map<int, int> lookup;\n        for (const auto& mask : masks) {  // Time: O(m * 2^m)\n            lookup[mask] = normalize(basis, mask);\n        }\n        unordered_map<int, int> normalized_mask_cnt;\n        for (const auto& mask : masks) {\n            normalized_mask_cnt[lookup[mask]] = (normalized_mask_cnt[lookup[mask]] + 1) % MOD;\n        }\n        assert(size(normalized_mask_cnt) == 3 * pow(2, m - 1) / 3 / (m >= 2 ? 2 : 1));  // divided by 3 * 2 is since the first two colors are normalized to speed up performance\n        unordered_map<int, vector<int>> adj;\n        for (const auto& [mask, _] : normalized_mask_cnt) {  // O(3^m) leaves which are all in depth m => Time: O(3^m), Space: O(3^m)\n            backtracking(mask, -1, basis, &adj[mask]);\n        }\n        unordered_map<int, unordered_map<int, int>> normalized_adj;\n        for (const auto& [mask1, mask2s] : adj) {\n            for (const auto& mask2 : mask2s) {\n                normalized_adj[mask1][lookup[mask2]] = (normalized_adj[mask1][lookup[mask2]] + 1) % MOD;\n            }\n        }\n        // divided by 3 * 2 is since the first two colors in upper row are normalized to speed up performance\n        assert(accumulate(cbegin(normalized_adj), cend(normalized_adj), 0,\n                          [](const auto& total, const auto& kvp) {\n                              return total + size(kvp.second);\n                          }) <= 2 * pow(3, m) / 3 / 2);\n        // since first two colors in lower row which has at most 3 choices could be also normalized, lower bound is upper bound divided by at most 3\n        assert(accumulate(cbegin(normalized_adj), cend(normalized_adj), 0,\n                          [](const auto& total, const auto& kvp) {\n                              return total + size(kvp.second);\n                          }) >= 2 * pow(3, m) / 3 / 2 / 3);\n        vector<vector<int>> matrix;\n        vector<vector<int>> counts(1);\n        for (const auto& [mask1, cnt] : normalized_mask_cnt) {\n            matrix.emplace_back();\n            for (const auto& [mask2, cnt] : normalized_mask_cnt)  {\n                matrix.back().emplace_back(normalized_adj[mask1][mask2]);\n            }\n            counts[0].emplace_back(cnt);\n        }\n        const auto& result = matrixMult(counts, matrixExpo(matrix, n - 1));  // Time: O((2^m)^3 * logn), Space: O((2^m)^2)\n        return accumulate(cbegin(result[0]), cend(result[0]), 0,\n                          [](const auto& total, const auto& x) {\n                              return (total + x) % MOD;\n                          });  // Time: O(2^m)\n    }\n\nprivate:\n    void backtracking(int mask1, int mask2, int basis, vector<int> *result) {  // Time: O(2^m), Space: O(2^m)\n        if (!basis) {\n            result->emplace_back(mask2);\n            return;\n        }\n        for (int i = 0; i < 3; ++i) {\n            if ((mask1 == -1 || mask1 / basis % 3 != i) && (mask2 == -1 || mask2 / (basis * 3) % 3 != i)) {\n                backtracking(mask1, mask2 != -1 ? mask2 + i * basis : i * basis, basis / 3, result);\n            }\n        }\n    }\n\n    vector<vector<int>> matrixExpo(const vector<vector<int>>& A, int pow) {\n        vector<vector<int>> result(A.size(), vector<int>(A.size()));\n        vector<vector<int>> A_exp(A);\n        for (int i = 0; i < A.size(); ++i) {\n            result[i][i] = 1;\n        }\n        while (pow) {\n            if (pow % 2 == 1) {\n                result = matrixMult(result, A_exp);\n            }\n            A_exp = matrixMult(A_exp, A_exp);\n            pow /= 2;\n        }\n        return result;\n    }\n\n    vector<vector<int>> matrixMult(const vector<vector<int>>& A, const vector<vector<int>>& B) {\n        vector<vector<int>> result(A.size(), vector<int>(B[0].size()));\n        for (int i = 0; i < A.size(); ++i) {\n            for (int j = 0; j < B[0].size(); ++j) {\n                int64_t entry = 0;\n                for (int k = 0; k < B.size(); ++k) {\n                    entry = (static_cast<int64_t>(A[i][k]) * B[k][j] % MOD + entry) % MOD;\n                }\n                result[i][j] = static_cast<int>(entry);\n            }\n        }\n        return result;\n    }\n\n    int normalize(int basis, int mask) {\n        unordered_map<int, int> norm;\n        int result = 0;\n        for (; basis; basis /= 3) {\n            int x = mask / basis % 3;\n            if (!norm.count(x)) {\n                norm[x] = size(norm);\n            }\n            result += norm[x] * basis;\n        }\n        return result;\n    }\n\n    static const int MOD = 1e9 + 7;\n};\n\n// Time:  O(n * 3^m)\n// Space: O(3^m)\n// better complexity for small m, large n\nclass Solution2 {\npublic:\n    int colorTheGrid(int m, int n) {\n        static const int MOD = 1e9 + 7;\n\n        if (m > n) {\n            swap(m, n);\n        }\n        const int basis = pow(3, m - 1);\n        const auto& masks = find_masks(m, basis);  // alternative of backtracking, Time: O(2^m), Space: O(2^m)\n        assert(size(masks) == 3 * pow(2, m - 1));\n        unordered_map<int, int> lookup;\n        for (const auto& mask : masks) {  // Time: O(m * 2^m)\n            lookup[mask] = normalize(basis, mask);\n        }\n        unordered_map<int, int> dp;\n        for (const auto& mask : masks) {  // normalize colors to speed up performance\n            ++dp[lookup[mask]];\n        }\n        const auto& adj = find_adj(m, basis, dp);  // alternative of backtracking, Time: O(3^m), Space: O(3^m)\n        // proof:\n        //   'o' uses the same color with its bottom-left one, \n        //   'x' uses the remaining color different from its left one and bottom-left one,\n        //   k is the cnt of 'o', \n        //    [3, 1(o), 1(x), 1(o), ..., 1(o), 1(x)] => nCr(m-1, k) * 3 * 2 * 2^k for k in xrange(m) = 3 * 2 * (2+1)^(m-1) = 2*3^m combinations\n        //    [2,    2,    1,    2, ...,  2,      1]\n        // another proof:\n        //   given previous pair of colors, each pair of '?' has 3 choices of colors\n        //     [3, ?, ?, ..., ?] => 3 * 2 * 3^(m-1) = 2*3^m combinations\n        //         |  |       |\n        //         3  3       3\n        //         |  |       |\n        //     [2, ?, ?, ..., ?]\n        unordered_map<int, unordered_map<int, int>> normalized_adj;\n        for (const auto& [mask1, mask2s] : adj) {\n            for (const auto& mask2 : mask2s) {\n                normalized_adj[lookup[mask1]][lookup[mask2]] = (normalized_adj[lookup[mask1]][lookup[mask2]] + 1) % MOD;\n            }\n        }\n        // divided by 3 * 2 is since the first two colors in upper row are normalized to speed up performance\n        assert(accumulate(cbegin(normalized_adj), cend(normalized_adj), 0,\n                          [](const auto& total, const auto& kvp) {\n                              return total + size(kvp.second);\n                          }) <= 2 * pow(3, m) / 3 / 2);\n        // since first two colors in lower row which has at most 3 choices could be also normalized, lower bound is upper bound divided by at most 3\n        assert(accumulate(cbegin(normalized_adj), cend(normalized_adj), 0,\n                          [](const auto& total, const auto& kvp) {\n                              return total + size(kvp.second);\n                          }) >= 2 * pow(3, m) / 3 / 2 / 3);\n        for (int i = 0; i < n - 1; ++i) {  // Time: O(n * 3^m), Space: O(2^m)\n            assert(size(dp) == 3 * pow(2, m - 1) / 3 / (m >= 2 ? 2 : 1));  // divided by 3 * 2 is since the first two colors are normalized to speed up performance\n            unordered_map<int, int> new_dp;\n            for (const auto [mask, v] : dp) {\n                for (const auto& [new_mask, cnt] : normalized_adj[mask]) {\n                    new_dp[lookup[new_mask]] = (new_dp[lookup[new_mask]] + (v * int64_t(cnt)) % MOD) % MOD;\n                }\n            }\n            dp = move(new_dp);\n        }\n        return accumulate(cbegin(dp), cend(dp), 0,\n                          [](const auto& total, const auto& kvp) {\n                              return (total + kvp.second) % MOD;\n                          });  // Time: O(2^m)\n    }\n\nprivate:\n    vector<int> find_masks(int m, int basis) {  // Time: 3 + 3*2 + 3*2*2 + ... + 3*2^(m-1) = 3 * (2^m - 1) = O(2^m), Space: O(2^m)\n        vector<int> masks = {0};\n        for (int c = 0; c < m; ++c) {\n            vector<int> new_masks;\n            for (const auto& mask : masks) {\n                vector<bool> used(3);\n                if (c > 0) {\n                    used[mask / basis] = true;  // get left grid\n                }\n                for (int x = 0; x < 3; ++x) {\n                    if (used[x]) {\n                        continue;\n                    }\n                    new_masks.emplace_back((x * basis) + (mask / 3));  // encoding mask\n                }\n            }\n            masks = move(new_masks);\n        }\n        return masks;\n    }\n\n    unordered_map<int, vector<int>> find_adj(int m, int basis, const unordered_map<int, int>& dp) {\n        // Time:  3*2^(m-1) * (1 + 2 + 2 * (3/2) + 2 * (3/2)^2 + ... + 2 * (3/2)^(m-2)) =\n        //        3*2^(m-1) * (1+2*((3/2)^(m-1)-1)/((3/2)-1)) =\n        //        3*2^(m-1) * (1+4*((3/2)^(m-1)-1)) =\n        //        3*2^(m-1) * (4*(3/2)^(m-1)-3) =\n        //        4*3^m-9*2^(m-1) =\n        //        O(3^m),\n        // Space: O(3^m)\n        unordered_map<int, vector<int>> adj;\n        for (const auto& [mask, _] : dp) {  // O(2^m)\n            adj[mask].emplace_back(mask);\n        }\n        for (int c = 0; c < m; ++c) {\n            assert(accumulate(cbegin(adj), cend(adj), 0,\n                              [](const auto& total, const auto& kvp) {\n                                  return total + size(kvp.second);\n                              }) == (c ? pow(3, c) * pow(2, m - (c - 1)) : 3 * pow(2, m - 1)) / 3 / (m >= 2 ? 2 : 1));  // divided by 3 * 2 is since the first two colors are normalized to speed up performance\n            unordered_map<int, vector<int>> new_adj;\n            for (const auto& [mask1, mask2s] : adj) {\n                for (const auto& mask : mask2s) {\n                    vector<bool> used(3);\n                    used[mask % 3] = true;  // get up grid\n                    if (c > 0) {\n                        used[mask / basis] = true;  // get left grid\n                    }\n                    for (int x = 0; x < 3; ++x) {\n                        if (used[x]) {\n                            continue;\n                        }\n                        new_adj[mask1].emplace_back((x * basis) + (mask / 3));  // encoding mask\n                    }\n                }\n            }\n            adj = move(new_adj);\n        }\n        return adj;\n    }\n \n    int normalize(int basis, int mask) {\n        unordered_map<int, int> norm;\n        int result = 0;\n        for (; basis; basis /= 3) {\n            int x = mask / basis % 3;\n            if (!norm.count(x)) {\n                norm[x] = size(norm);\n            }\n            result += norm[x] * basis;\n        }\n        return result;\n    }\n};\n\n// Time:  (m * n grids) * (O(3*3*2^(m-2)) possible states per grid) = O(n * m * 2^m)\n// Space: O(3*3*2^(m-2)) = O(2^m)\n// better complexity for large m, large n\nclass Solution3 {\npublic:\n    int colorTheGrid(int m, int n) {\n        static const int MOD = 1e9 + 7;\n\n        if (m > n) {\n            swap(m, n);\n        }\n        const int basis = pow(3, m - 1);\n        int b = basis;\n        unordered_map<int, unordered_map<int, int>> lookup;\n        unordered_map<int, int> dp = {{0, 1}};\n        for (int idx = 0; idx < m * n; ++idx) {\n            int r = idx / m;\n            int c = idx % m;\n            // sliding window with size m doesn't cross rows:\n            //   [3, 2, ..., 2] => 3*2^(m-1) combinations\n            assert(r != 0 || c != 0 || size(dp) == 1);\n            assert(r != 0 || c == 0 || size(dp) == 3 * pow(2, c - 1) / 3 / (c >= 2 ? 2 : 1));  // divided by 3 * 2 is since the first two colors are normalized to speed up performance\n            assert(r == 0 || c != 0 || size(dp) == 3 * pow(2, m - 1) / 3 / (m >= 2 ? 2 : 1));  // divided by 3 * 2 is since the first two colors are normalized to speed up performance\n            // sliding window with size m crosses rows:\n            //   [*, ..., *, *, 3, 2, ..., 2] => 3*3 * 2^(m-2) combinations\n            //   [2, ..., 2, 3, *, *, ..., *]\n            assert(r == 0 || c == 0 || size(dp) == (m == 1 ? 1 : m == 2 ? 2 : (3 * 3 * pow(2, m - 2) / 3 / 2)));  // divided by 3 * 2 for m >= 3 is since the first two colors of window are normalized to speed up performance\n            unordered_map<int, int> new_dp;\n            for (const auto [mask, v] : dp) {\n                vector<bool> used(3);\n                if (r > 0) {\n                    used[mask % 3] = true;  // get up grid\n                }\n                if (c > 0) {\n                    used[mask / basis] = true;  // get left grid\n                }\n                for (int x = 0; x < 3; ++x) {\n                    if (used[x]) {\n                        continue;\n                    }\n                    const auto new_mask = normalize(basis / b, ((x * basis) + (mask / 3)) / b, &lookup) * b;  // encoding mask\n                    new_dp[new_mask] = (new_dp[new_mask] + v) % MOD;\n                }\n            }\n            if (b > 1) {\n                b /= 3;\n            }\n            dp = move(new_dp);\n        }\n        return accumulate(cbegin(dp), cend(dp), 0,\n                          [](const auto& total, const auto& kvp) {\n                              return (total + kvp.second) % MOD;\n                          });  // Time: O(2^m)\n    }\n\n    int normalize(int basis, int mask, unordered_map<int, unordered_map<int, int>> *lookup) {  // compute and cache, at most O(3*2^(m-3)) time and space\n        if (!(*lookup)[basis].count(mask)) {\n            unordered_map<int, int> norm;\n            int result = 0;\n            for (int b = basis; b; b /= 3) {\n                int x = mask / b % 3;\n                if (!norm.count(x)) {\n                    norm[x] = size(norm);\n                }\n                result += norm[x] * b;\n            }\n            (*lookup)[basis][mask] = result;\n        }\n        return (*lookup)[basis][mask];\n    }\n};",
      "timeComplexity": "",
      "spaceComplexity": ""
    },
    {
      "language": "python",
      "code": "# Time:  O(m * 2^m + 3^m + 2^(3 * m) * logn) = O(2^(3 * m) * logn)\n# Space: O(2^(2 * m))\n\nimport collections\nimport itertools\n\n\n# better complexity for small m, super large n\n# matrix exponentiation solution\nclass Solution(object):\n    def colorTheGrid(self, m, n):\n        \"\"\"\n        :type m: int\n        :type n: int\n        :rtype: int\n        \"\"\"\n        MOD = 10**9+7\n        def backtracking(mask1, mask2, basis, result):  # Time: O(2^m), Space: O(2^m)\n            if not basis:\n                result.append(mask2)\n                return\n            for i in xrange(3):\n                if (mask1 == -1 or mask1//basis%3 != i) and (mask2 == -1 or mask2//(basis*3)%3 != i):\n                    backtracking(mask1, mask2+i*basis if mask2 != -1 else i*basis, basis//3, result)\n\n        def matrix_mult(A, B):\n            ZB = zip(*B)\n            return [[sum(a*b % MOD for a, b in itertools.izip(row, col)) % MOD for col in ZB] for row in A]\n \n        def matrix_expo(A, K):\n            result = [[int(i == j) for j in xrange(len(A))] for i in xrange(len(A))]\n            while K:\n                if K % 2:\n                    result = matrix_mult(result, A)\n                A = matrix_mult(A, A)\n                K /= 2\n            return result\n\n        def normalize(basis, mask):\n            norm = {}\n            result = 0\n            while basis:\n                x = mask//basis%3\n                if x not in norm:\n                    norm[x] = len(norm)\n                result += norm[x]*basis\n                basis //= 3\n            return result\n\n        if m > n:\n            m, n = n, m\n        basis = 3**(m-1)\n        masks = []\n        backtracking(-1, -1, basis, masks)  # Time: O(2^m), Space: O(2^m)\n        assert(len(masks) == 3 * 2**(m-1))\n        lookup = {mask:normalize(basis, mask) for mask in masks}  # Time: O(m * 2^m)\n        normalized_mask_cnt = collections.Counter(lookup[mask] for mask in masks)\n        assert(len(normalized_mask_cnt) == 3*2**(m-1) // 3 // (2 if m >= 2 else 1))  # divided by 3 * 2 is since the first two colors are normalized to speed up performance\n        adj = collections.defaultdict(list)\n        for mask in normalized_mask_cnt.iterkeys():  # O(3^m) leaves which are all in depth m => Time: O(3^m), Space: O(3^m)\n            backtracking(mask, -1, basis, adj[mask])\n        normalized_adj = collections.defaultdict(lambda:collections.defaultdict(int))\n        for mask1, masks2 in adj.iteritems():\n            for mask2 in masks2:\n                normalized_adj[mask1][lookup[mask2]] = (normalized_adj[mask1][lookup[mask2]]+1)%MOD\n        # divided by 3 * 2 is since the first two colors in upper row are normalized to speed up performance,\n        # since first two colors in lower row which has at most 3 choices could be also normalized, lower bound is upper bound divided by at most 3\n        assert(2*3**m // 3 // 2 // 3 <= sum(len(v) for v in normalized_adj.itervalues()) <= 2*3**m // 3 // 2)\n        return reduce(lambda x,y: (x+y)%MOD,\n                      matrix_mult([normalized_mask_cnt.values()],\n                                   matrix_expo([[normalized_adj[mask1][mask2]\n                                                 for mask2 in normalized_mask_cnt.iterkeys()] \n                                                 for mask1 in normalized_mask_cnt.iterkeys()], n-1))[0],\n                      0)  # Time: O((2^m)^3 * logn), Space: O((2^m)^2)\n\n\n# Time:  O(n * 3^m)\n# Space: O(3^m)\nimport collections\n\n\n# better complexity for small m, large n\nclass Solution2(object):\n    def colorTheGrid(self, m, n):\n        \"\"\"\n        :type m: int\n        :type n: int\n        :rtype: int\n        \"\"\"\n        MOD = 10**9+7\n        def find_masks(m, basis):  # Time: 3 + 3*2 + 3*2*2 + ... + 3*2^(m-1) = 3 * (2^m - 1) = O(2^m), Space: O(2^m)\n            masks = [0]\n            for c in xrange(m):\n                new_masks = []\n                for mask in masks:\n                    choices = {0, 1, 2}\n                    if c > 0:\n                        choices.discard(mask//basis)  # get left grid\n                    for x in choices:\n                        new_masks.append((x*basis)+(mask//3))  # encoding mask\n                masks = new_masks\n            return masks\n\n        def find_adj(m, basis, dp):\n            # Time:  3*2^(m-1) * (1 + 2 + 2 * (3/2) + 2 * (3/2)^2 + ... + 2 * (3/2)^(m-2)) =\n            #        3*2^(m-1) * (1+2*((3/2)^(m-1)-1)/((3/2)-1)) =\n            #        3*2^(m-1) * (1+4*((3/2)^(m-1)-1)) =\n            #        3*2^(m-1) * (4*(3/2)^(m-1)-3) =\n            #        4*3^m-9*2^(m-1) =\n            #        O(3^m),\n            # Space: O(3^m)\n            adj = collections.defaultdict(list)\n            for mask in dp.iterkeys():  # O(2^m)\n                adj[mask].append(mask)\n            for c in xrange(m):\n                assert(sum(len(v) for v in adj.itervalues()) == (3**c * 2**(m-(c-1)) if c >= 1 else 3 * 2**(m-1)) // 3 // (2 if m >= 2 else 1))  # divided by 3 * 2 is since the first two colors are normalized to speed up performance\n                new_adj = collections.defaultdict(list)\n                for mask1, mask2s in adj.iteritems():\n                    for mask in mask2s:\n                        choices = {0, 1, 2}\n                        choices.discard(mask%3)  # get up grid\n                        if c > 0:\n                            choices.discard(mask//basis)  # get left grid\n                        for x in choices:\n                            new_adj[mask1].append((x*basis)+(mask//3))  # encoding mask\n                adj = new_adj\n            assert(sum(3**c * 2**(m-(c-1)) if c >= 1 else 3 * 2**(m-1) for c in xrange(m)) == 4*3**m-9*2**(m-1))\n            return adj\n \n        def normalize(basis, mask):\n            norm = {}\n            result = 0\n            while basis:\n                x = mask//basis%3\n                if x not in norm:\n                    norm[x] = len(norm)\n                result += norm[x]*basis\n                basis //= 3\n            return result\n\n        if m > n:\n            m, n = n, m\n        basis = 3**(m-1)\n        masks = find_masks(m, basis)  # alternative of backtracking, Time: O(2^m), Space: O(2^m)\n        assert(len(masks) == 3 * 2**(m-1))\n        lookup = {mask:normalize(basis, mask) for mask in masks}  # Time: O(m * 2^m)\n        dp = collections.Counter(lookup[mask] for mask in masks)  # normalize colors to speed up performance\n        adj = find_adj(m, basis, dp)  # alternative of backtracking, Time: O(3^m), Space: O(3^m)\n        # proof:\n        #   'o' uses the same color with its bottom-left one, \n        #   'x' uses the remaining color different from its left one and bottom-left one,\n        #   k is the cnt of 'o', \n        #     [3, 1(o), 1(x), 1(o), ..., 1(o), 1(x)] => nCr(m-1, k) * 3 * 2 * 2^k for k in xrange(m) = 3 * 2 * (2+1)^(m-1) = 2*3^m combinations\n        #     [2,    2,    1,    2, ...,  2,      1]\n        # another proof:\n        #   given previous pair of colors, each pair of '?' has 3 choices of colors\n        #     [3, ?, ?, ..., ?] => 3 * 2 * 3^(m-1) = 2*3^m combinations\n        #         |  |       |\n        #         3  3       3\n        #         |  |       |\n        #     [2, ?, ?, ..., ?]\n        normalized_adj = collections.defaultdict(lambda:collections.defaultdict(int))\n        for mask1, mask2s in adj.iteritems():\n            for mask2 in mask2s:\n                normalized_adj[lookup[mask1]][lookup[mask2]] = (normalized_adj[lookup[mask1]][lookup[mask2]]+1)%MOD\n        # divided by 3 * 2 is since the first two colors in upper row are normalized to speed up performance,\n        # since first two colors in lower row which has at most 3 choices could be also normalized, lower bound is upper bound divided by at most 3\n        assert(2*3**m // 3 // 2 // 3 <= sum(len(v) for v in normalized_adj.itervalues()) <= 2*3**m // 3 // 2)\n        for _ in xrange(n-1):  # Time: O(n * 3^m), Space: O(2^m)\n            assert(len(dp) == 3*2**(m-1) // 3 // (2 if m >= 2 else 1))  # divided by 3 * 2 is since the first two colors are normalized to speed up performance\n            new_dp = collections.Counter()\n            for mask, v in dp.iteritems():\n                for new_mask, cnt in normalized_adj[mask].iteritems():\n                    new_dp[lookup[new_mask]] = (new_dp[lookup[new_mask]] + v*cnt) % MOD\n            dp = new_dp\n        return reduce(lambda x,y: (x+y)%MOD, dp.itervalues(), 0)  # Time: O(2^m)\n\n\n# Time:  (m * n grids) * (O(3*3*2^(m-2)) possible states per grid) = O(n * m * 2^m)\n# Space: O(3*3*2^(m-2)) = O(2^m)\nimport collections\n\n\n# better complexity for large m, large n\nclass Solution3(object):\n    def colorTheGrid(self, m, n):\n        \"\"\"\n        :type m: int\n        :type n: int\n        :rtype: int\n        \"\"\"\n        MOD = 10**9+7\n        def normalize(basis, mask, lookup):  # compute and cache, at most O(3*2^(m-3)) time and space\n            if mask not in lookup[basis]:\n                norm = {}\n                result, b = 0, basis\n                while b:\n                    x = mask//b%3\n                    if x not in norm:\n                        norm[x] = len(norm)\n                    result += norm[x]*b\n                    b //= 3\n                lookup[basis][mask] = result\n            return lookup[basis][mask]\n\n        if m > n:\n            m, n = n, m\n        basis = b = 3**(m-1)\n        lookup = collections.defaultdict(dict)\n        dp = collections.Counter({0: 1})\n        for idx in xrange(m*n):\n            r, c = divmod(idx, m)\n            # sliding window with size m doesn't cross rows:\n            #   [3, 2, ..., 2] => 3*2^(m-1) combinations\n            assert(r != 0 or c != 0 or len(dp) == 1)\n            assert(r != 0 or c == 0 or len(dp) == 3*2**(c-1) // 3 // (2 if c >= 2 else 1))  # divided by 3 * 2 is since the first two colors are normalized to speed up performance\n            assert(r == 0 or c != 0 or len(dp) == 3*2**(m-1) // 3 // (2 if m >= 2 else 1))  # divided by 3 * 2 is since the first two colors are normalized to speed up performance\n            # sliding window with size m crosses rows:\n            #   [*, ..., *, *, 3, 2, ..., 2] => 3*3 * 2^(m-2) combinations\n            #   [2, ..., 2, 3, *, *, ..., *]\n            assert(r == 0 or c == 0 or len(dp) == (1 if m == 1 else 2 if m == 2 else 3*3 * 2**(m-2) // 3 // 2))  # divided by 3 * 2 for m >= 3 is since the first two colors of window are normalized to speed up performance\n            new_dp = collections.Counter()\n            for mask, v in dp.iteritems():\n                choices = {0, 1, 2}\n                if r > 0:\n                    choices.discard(mask%3)  # get up grid\n                if c > 0:\n                    choices.discard(mask//basis)  # get left grid\n                for x in choices:\n                    new_mask = normalize(basis//b, ((x*basis)+(mask//3))//b, lookup)*b  # encoding mask\n                    new_dp[new_mask] = (new_dp[new_mask]+v)%MOD\n            if b > 1:\n                b //= 3\n            dp = new_dp\n        return reduce(lambda x,y: (x+y)%MOD, dp.itervalues(), 0)  # Time: O(2^m)",
      "timeComplexity": "",
      "spaceComplexity": ""
    }
  ],
  "editorial": {
    "approach": "",
    "explanation": "",
    "keyInsight": "",
    "commonMistakes": []
  }
}